patch_denoise/__init__.py
patch_denoise/_docs.py
patch_denoise/_version.py
patch_denoise/denoise.py
patch_denoise/bindings/__init__.py
patch_denoise/bindings/cli.py
patch_denoise/bindings/modopt.py
patch_denoise/bindings/nipype.py
patch_denoise/bindings/utils.py
patch_denoise/simulation/__init__.py
patch_denoise/simulation/activations.py
patch_denoise/simulation/noise.py
patch_denoise/simulation/phantom.py
patch_denoise/space_time/__init__.py
patch_denoise/space_time/base.py
patch_denoise/space_time/lowrank.py
patch_denoise/space_time/utils.py
patch_denoise-1.4.4.dist-info/licenses/LICENSE.txt
patch_denoise-1.4.4.dist-info/METADATA
patch_denoise-1.4.4.dist-info/WHEEL
patch_denoise-1.4.4.dist-info/entry_points.txt
patch_denoise-1.4.4.dist-info/top_level.txt
patch_denoise-1.4.4.dist-info/RECORD
