Metadata-Version: 2.4
Name: patch-denoise
Version: 1.4.4
Summary: Denoising method for sequence of images or volumes. Primarily targeting fMRI data.
Author-email: Pierre-antoine Comby <pierre-antoine.comby@crans.org>
License: MIT License
Classifier: Development Status :: 3 - Alpha
Classifier: Environment :: Console
Classifier: Intended Audience :: Science/Research
Classifier: License :: OSI Approved :: MIT License
Classifier: Operating System :: OS Independent
Classifier: Programming Language :: Python
Classifier: Programming Language :: Python :: 3.9
Classifier: Programming Language :: Python :: 3.10
Classifier: Programming Language :: Python :: 3.11
Classifier: Programming Language :: Python :: 3.12
Classifier: Programming Language :: Python :: 3 :: Only
Classifier: Topic :: Scientific/Engineering :: Image Processing
Classifier: Topic :: Scientific/Engineering :: Medical Science Apps.
Requires-Python: >=3.9
License-File: LICENSE.txt
Requires-Dist: numpy
Requires-Dist: scipy
Requires-Dist: matplotlib
Requires-Dist: scikit-image
Requires-Dist: tqdm
Requires-Dist: nibabel
Provides-Extra: optional
Requires-Dist: modopt; extra == "optional"
Requires-Dist: nipype; extra == "optional"
Requires-Dist: numba; extra == "optional"
Provides-Extra: test
Requires-Dist: pytest; extra == "test"
Requires-Dist: pytest-cov; extra == "test"
Requires-Dist: pytest-xdist; extra == "test"
Requires-Dist: pytest-sugar; extra == "test"
Provides-Extra: doc
Requires-Dist: pydata-sphinx-theme; extra == "doc"
Requires-Dist: numpydoc; extra == "doc"
Requires-Dist: sphinx_gallery; extra == "doc"
Requires-Dist: sphinx-argparse; extra == "doc"
Requires-Dist: sphinx; extra == "doc"
Provides-Extra: dev
Requires-Dist: black; extra == "dev"
Requires-Dist: isort; extra == "dev"
Requires-Dist: ruff; extra == "dev"
Dynamic: license-file
